odoo/addons/procurement_auto_create_group/README.rst
odoo/addons/procurement_auto_create_group/__init__.py
odoo/addons/procurement_auto_create_group/__manifest__.py
odoo/addons/procurement_auto_create_group/i18n/ca.po
odoo/addons/procurement_auto_create_group/i18n/cs_CZ.po
odoo/addons/procurement_auto_create_group/i18n/de.po
odoo/addons/procurement_auto_create_group/i18n/es.po
odoo/addons/procurement_auto_create_group/i18n/es_MX.po
odoo/addons/procurement_auto_create_group/i18n/fr.po
odoo/addons/procurement_auto_create_group/i18n/hr.po
odoo/addons/procurement_auto_create_group/i18n/it.po
odoo/addons/procurement_auto_create_group/i18n/procurement_auto_create_group.pot
odoo/addons/procurement_auto_create_group/i18n/pt_BR.po
odoo/addons/procurement_auto_create_group/i18n/pt_PT.po
odoo/addons/procurement_auto_create_group/i18n/ro.po
odoo/addons/procurement_auto_create_group/i18n/sk.po
odoo/addons/procurement_auto_create_group/i18n/sl.po
odoo/addons/procurement_auto_create_group/i18n/tr_TR.po
odoo/addons/procurement_auto_create_group/i18n/vi_VN.po
odoo/addons/procurement_auto_create_group/i18n/zh_CN.po
odoo/addons/procurement_auto_create_group/models/__init__.py
odoo/addons/procurement_auto_create_group/models/procurement_group.py
odoo/addons/procurement_auto_create_group/models/stock_rule.py
odoo/addons/procurement_auto_create_group/readme/CONFIGURE.md
odoo/addons/procurement_auto_create_group/readme/CONTRIBUTORS.md
odoo/addons/procurement_auto_create_group/readme/DESCRIPTION.md
odoo/addons/procurement_auto_create_group/readme/USAGE.md
odoo/addons/procurement_auto_create_group/static/description/icon.png
odoo/addons/procurement_auto_create_group/static/description/index.html
odoo/addons/procurement_auto_create_group/tests/__init__.py
odoo/addons/procurement_auto_create_group/tests/test_auto_create.py
odoo/addons/procurement_auto_create_group/views/procurement_view.xml
odoo_addon_procurement_auto_create_group-18.0.1.0.1.dist-info/METADATA
odoo_addon_procurement_auto_create_group-18.0.1.0.1.dist-info/WHEEL
odoo_addon_procurement_auto_create_group-18.0.1.0.1.dist-info/top_level.txt
odoo_addon_procurement_auto_create_group-18.0.1.0.1.dist-info/RECORD
