Metadata-Version: 2.1
Name: odoo-addon-procurement_auto_create_group
Version: 18.0.1.0.1
Requires-Python: >=3.10
Requires-Dist: odoo==18.0.*
Summary: Allows to configure the system to propose automatically new procurement groups during the procurement run.
Home-page: https://github.com/OCA/stock-logistics-warehouse
License: AGPL-3
Author: ForgeFlow, BCIM, Odoo Community Association (OCA)
Author-email: support@odoo-community.org
Classifier: Programming Language :: Python
Classifier: Framework :: Odoo
Classifier: Framework :: Odoo :: 18.0
Classifier: License :: OSI Approved :: GNU Affero General Public License v3
Classifier: Development Status :: 5 - Production/Stable
